xlcsv/__init__.py
xlcsv/error.py
xlcsv/io.py
xlcsv/utils.py
xlcsv-0.3.0.dist-info/LICENSE
xlcsv-0.3.0.dist-info/WHEEL
xlcsv-0.3.0.dist-info/METADATA
xlcsv-0.3.0.dist-info/RECORD
