Metadata-Version: 2.1
Name: xlcsv
Version: 0.3.0
Summary: A Python micropackage for consuming Excel as CSV.
Home-page: https://github.com/cnpryer/xlcsv.git
License: MIT
Author: Chris Pryer
Author-email: cnpryer@gmail.com
Requires-Python: >=3.8,<4.0
Classifier: License :: OSI Approved :: MIT License
Classifier: Programming Language :: Python :: 3
Classifier: Programming Language :: Python :: 3.10
Classifier: Programming Language :: Python :: 3.8
Classifier: Programming Language :: Python :: 3.9
Requires-Dist: openpyxl (>=3.0.10,<4.0.0)
Project-URL: Repository, https://github.com/cnpryer/xlcsv.git
